cyvcf2/__init__.py
cyvcf2/__main__.py
cyvcf2/cli.py
cyvcf2/cyvcf2.c
cyvcf2/cyvcf2.cpython-314-x86_64-linux-gnu.so
cyvcf2/cyvcf2.pxd
cyvcf2/cyvcf2.pyx
cyvcf2/helpers.c
cyvcf2/helpers.h
cyvcf2/relatedness.h
cyvcf2.libs/libbz2-a273e504.so.1.0.6
cyvcf2.libs/libcom_err-2abe824b.so.2.1
cyvcf2.libs/libcrypt-a115dc8d.so.1
cyvcf2.libs/libcrypto-d3570994.so.1.0.2k
cyvcf2.libs/libcurl-34c6b10f.so.4.3.0
cyvcf2.libs/libdeflate-3c69c952.so.0
cyvcf2.libs/libgssapi_krb5-497db0c6.so.2.2
cyvcf2.libs/libidn-97d26f25.so.11.6.11
cyvcf2.libs/libk5crypto-b1f99d5c.so.3.1
cyvcf2.libs/libkeyutils-dfe70bd6.so.1.5
cyvcf2.libs/libkrb5-fcafa220.so.3.3
cyvcf2.libs/libkrb5support-d0bcff84.so.0.1
cyvcf2.libs/liblber-2-7eefa761.4.so.2.10.7
cyvcf2.libs/libldap-2-b8523ca2.4.so.2.10.7
cyvcf2.libs/liblzma-004595ca.so.5.2.2
cyvcf2.libs/libnspr4-4c890ba1.so
cyvcf2.libs/libnss3-77677daf.so
cyvcf2.libs/libnssutil3-3492aa84.so
cyvcf2.libs/libpcre-9513aab5.so.1.2.0
cyvcf2.libs/libplc4-690d9cce.so
cyvcf2.libs/libplds4-c4b42550.so
cyvcf2.libs/libsasl2-84219a89.so.3.0.0
cyvcf2.libs/libselinux-0922c95c.so.1
cyvcf2.libs/libsmime3-1ce58481.so
cyvcf2.libs/libssh2-eaeb651a.so.1.0.1
cyvcf2.libs/libssl-cd1d6220.so.1.0.2k
cyvcf2.libs/libssl3-b5783e6f.so
cyvcf2-0.31.4.dist-info/METADATA
cyvcf2-0.31.4.dist-info/WHEEL
cyvcf2-0.31.4.dist-info/entry_points.txt
cyvcf2-0.31.4.dist-info/top_level.txt
cyvcf2-0.31.4.dist-info/RECORD
cyvcf2-0.31.4.dist-info/licenses/LICENSE
