Metadata-Version: 2.4
Name: cyvcf2
Version: 0.31.4
Summary: fast vcf parsing with cython + htslib
Home-page: https://github.com/brentp/cyvcf2/
Author: Brent Pedersen
Author-email: bpederse@gmail.com
License: MIT
Requires-Python: >=3.7
License-File: LICENSE
Requires-Dist: numpy>=1.16.0
Requires-Dist: coloredlogs
Requires-Dist: click
Dynamic: author
Dynamic: author-email
Dynamic: description
Dynamic: description-content-type
Dynamic: home-page
Dynamic: license
Dynamic: license-file
Dynamic: requires-dist
Dynamic: requires-python
Dynamic: summary
